LICENSE
MANIFEST.in
README.rst
setup.py
geokey_dataimports/__init__.py
geokey_dataimports/base.py
geokey_dataimports/exceptions.py
geokey_dataimports/forms.py
geokey_dataimports/managers.py
geokey_dataimports/models.py
geokey_dataimports/urls.py
geokey_dataimports/views.py
geokey_dataimports.egg-info/PKG-INFO
geokey_dataimports.egg-info/SOURCES.txt
geokey_dataimports.egg-info/dependency_links.txt
geokey_dataimports.egg-info/top_level.txt
geokey_dataimports/helpers/__init__.py
geokey_dataimports/helpers/context_helpers.py
geokey_dataimports/helpers/model_helpers.py
geokey_dataimports/helpers/type_helpers.py
geokey_dataimports/migrations/0001_initial.py
geokey_dataimports/migrations/0002_auto_20160329_0957.py
geokey_dataimports/migrations/__init__.py
geokey_dataimports/static/css/dataimports.css
geokey_dataimports/static/img/marker-deselected.png
geokey_dataimports/static/img/marker-selected.png
geokey_dataimports/static/js/admin.ui.dataimports.js
geokey_dataimports/templates/di_add_dataimport.html
geokey_dataimports/templates/di_all_datafeatures.html
geokey_dataimports/templates/di_all_dataimports.html
geokey_dataimports/templates/di_assign_fields.html
geokey_dataimports/templates/di_create_category.html
geokey_dataimports/templates/di_index.html
geokey_dataimports/templates/di_single_dataimport.html
geokey_dataimports/templates/snippets/di_breadcrumb.html
geokey_dataimports/templates/snippets/di_header.html
geokey_dataimports/templates/snippets/di_loader.html
geokey_dataimports/templatetags/__init__.py
geokey_dataimports/templatetags/di_tags.py