Metadata-Version: 1.1
Name: geokey-dataimports
Version: 0.4.1
Summary: Import data from various formats into GeoKey
Home-page: https://github.com/ExCiteS/geokey-dataimports
Author: ExCiteS
Author-email: excites@ucl.ac.uk
License: MIT
Download-URL: https://github.com/ExCiteS/geokey-dataimports/tarball/0.4.1
Platform: UNKNOWN
